PySide2extn/RoundProgressBar.py
PySide2extn/SpiralProgressBar.py
PySide2extn/__init__.py
PySide2extn/demo/__init__.py
PySide2extn/demo/demo.py
PySide2extn/examples/__init__.py
PySide2extn-1.0.0.dist-info/LICENSE
PySide2extn-1.0.0.dist-info/METADATA
PySide2extn-1.0.0.dist-info/WHEEL
PySide2extn-1.0.0.dist-info/top_level.txt
PySide2extn-1.0.0.dist-info/RECORD
