Metadata-Version: 2.1
Name: PySide2extn
Version: 1.0.0
Summary: PySide2extn is an Open Source Python Programming language extension for PySide2, which greatly enhances the capability of the PySide2 library with extra widgets and more.
Home-page: https://github.com/anjalp/PySide2extn
Author: ANJAL.P
Author-email: opensource.anj.official@gmail.com
License: UNKNOWN
Platform: UNKNOWN
Classifier: Development Status :: 5 - Production/Stable
Classifier: Intended Audience :: Developers
Classifier: Programming Language :: Python :: 3.5
Classifier: Programming Language :: Python :: 3.6
Classifier: Programming Language :: Python :: 3.7
Classifier: Programming Language :: Python :: 3.8
Classifier: Programming Language :: Python :: 3.9
Classifier: License :: OSI Approved :: MIT License
Classifier: Operating System :: OS Independent
Requires-Python: >=3.6
Requires-Dist: PySide2
